jakekap_de_toolkit/__init__.py
jakekap_de_toolkit/main.py
jakekap_de_toolkit/vm.py
jakekap_de_toolkit-0.1.0.dist-info/METADATA
jakekap_de_toolkit-0.1.0.dist-info/WHEEL
jakekap_de_toolkit-0.1.0.dist-info/entry_points.txt
jakekap_de_toolkit-0.1.0.dist-info/RECORD
