Metadata-Version: 2.4
Name: jakekap-de-toolkit
Version: 0.1.0
Summary: 
Author: Christian Andrade
Author-email: ce.andrade.p@gmail.com
Requires-Python: >=3.12
Classifier: Programming Language :: Python :: 3
Classifier: Programming Language :: Python :: 3.12
Classifier: Programming Language :: Python :: 3.13
Classifier: Programming Language :: Python :: 3.14
Requires-Dist: click (>=8.3.0,<9.0.0)
